deepspectrum/__init__.py
deepspectrum/__main__.py
deepspectrum/backend/__init__.py
deepspectrum/backend/extractor.py
deepspectrum/backend/plotting.py
deepspectrum/cli/__init__.py
deepspectrum/cli/configuration.py
deepspectrum/cli/deep.conf
deepspectrum/cli/features.py
deepspectrum/cli/features_with_parser.py
deepspectrum/cli/image_features.py
deepspectrum/cli/plot.py
deepspectrum/cli/utils.py
deepspectrum/tools/__init__.py
deepspectrum/tools/custom_arff.py
deepspectrum/tools/feature_writer.py
deepspectrum/tools/label_parser.py
deepspectrum/tools/path.py
DeepSpectrum-0.6.9.dist-info/LICENSE
DeepSpectrum-0.6.9.dist-info/METADATA
DeepSpectrum-0.6.9.dist-info/WHEEL
DeepSpectrum-0.6.9.dist-info/entry_points.txt
DeepSpectrum-0.6.9.dist-info/namespace_packages.txt
DeepSpectrum-0.6.9.dist-info/top_level.txt
DeepSpectrum-0.6.9.dist-info/RECORD
