Metadata-Version: 2.1
Name: DeepSpectrum
Version: 0.6.9
Summary: UNKNOWN
Home-page: https://github.com/DeepSpectrum/DeepSpectrum
Author: Maurice Gerczuk
Author-email: gerczuk@fim.uni-passau.de
License: GPLv3+
Project-URL: Source, https://github.com/DeepSpectrum/DeepSpectrum/
Project-URL: Tracker, https://github.com/DeepSpectrum/DeepSpectrum/issues
Keywords: machine-learning audio-analysis science research
Platform: Any
Classifier: Development Status :: 4 - Beta
Classifier: Environment :: GPU :: NVIDIA CUDA :: 10.0
Classifier: Topic :: Scientific/Engineering :: Artificial Intelligence
Classifier: Intended Audience :: Science/Research
Classifier: License :: OSI Approved :: GNU General Public License v3 (GPLv3)
Classifier: Programming Language :: Python :: 3.7
Requires-Python: ~=3.7.0
Requires-Dist: audeep (>=0.9.4)
Requires-Dist: imread (>=0.7.0)
Requires-Dist: tqdm (>=4.30.0)
Requires-Dist: matplotlib (>=3.3)
Requires-Dist: numba (==0.48.0)
Requires-Dist: librosa (<0.8.0,>=0.7.0)
Requires-Dist: click (>=7.0)
Requires-Dist: Pillow (>=6.0.0)
Requires-Dist: tensorflow-gpu (<2,>=1.15.2)
Requires-Dist: opencv-python (>=4.0.0.21)
Requires-Dist: torch (>=1.2.0)
Requires-Dist: torchvision (>=0.5.0)
